picardapi/Clone.py
picardapi/Mobile_uagent.py
picardapi/PhysioBank.py
picardapi/PicardApi.py
picardapi/Simulate.py
picardapi/__init__.py
picardapi-1.1.0.dist-info/LICENSE.txt
picardapi-1.1.0.dist-info/METADATA
picardapi-1.1.0.dist-info/WHEEL
picardapi-1.1.0.dist-info/top_level.txt
picardapi-1.1.0.dist-info/RECORD
